MANIFEST.in
README.rst
requirements.txt
setup.cfg
setup.py
django_microsip_exportaexcel/__init__.py
django_microsip_exportaexcel/__init__.pyc
django_microsip_exportaexcel/config.py
django_microsip_exportaexcel/config.pyc
django_microsip_exportaexcel/models.py
django_microsip_exportaexcel/models.pyc
django_microsip_exportaexcel/urls.py
django_microsip_exportaexcel/urls.pyc
django_microsip_exportaexcel/views.py
django_microsip_exportaexcel/views.pyc
django_microsip_exportaexcel.egg-info/PKG-INFO
django_microsip_exportaexcel.egg-info/SOURCES.txt
django_microsip_exportaexcel.egg-info/dependency_links.txt
django_microsip_exportaexcel.egg-info/requires.txt
django_microsip_exportaexcel.egg-info/top_level.txt
django_microsip_exportaexcel/templates/django_microsip_exportaexcel/base.html
django_microsip_exportaexcel/templates/django_microsip_exportaexcel/index.html